{"v":3,"stories":{"global-component--no-history":{"id":"global-component--no-history","title":"Global component","name":"No History","importPath":"./frontend/HistoryViewer.stories.ts"},"global-component--http-error":{"id":"global-component--http-error","title":"Global component","name":"Http Error","importPath":"./frontend/HistoryViewer.stories.ts"},"global-component--exception":{"id":"global-component--exception","title":"Global component","name":"Exception","importPath":"./frontend/HistoryViewer.stories.ts"},"global-component--with-history":{"id":"global-component--with-history","title":"Global component","name":"With History","importPath":"./frontend/HistoryViewer.stories.ts"},"global-component--filtering-on-tag":{"id":"global-component--filtering-on-tag","title":"Global component","name":"Filtering On Tag","importPath":"./frontend/HistoryViewer.stories.ts"},"global-component--only-one-mode":{"id":"global-component--only-one-mode","title":"Global component","name":"Only One Mode","importPath":"./frontend/HistoryViewer.stories.ts"},"global-component--two-modes-with-default":{"id":"global-component--two-modes-with-default","title":"Global component","name":"Two Modes With Default","importPath":"./frontend/HistoryViewer.stories.ts"},"tablehistory--no-history":{"id":"tablehistory--no-history","title":"TableHistory","name":"No History","importPath":"./frontend/components/TableHistory.stories.ts"},"tablehistory--with-history":{"id":"tablehistory--with-history","title":"TableHistory","name":"With History","importPath":"./frontend/components/TableHistory.stories.ts"},"tablehistory--dynamic":{"id":"tablehistory--dynamic","title":"TableHistory","name":"Dynamic","importPath":"./frontend/components/TableHistory.stories.ts"},"tablehistory--dynamic-empty":{"id":"tablehistory--dynamic-empty","title":"TableHistory","name":"Dynamic Empty","importPath":"./frontend/components/TableHistory.stories.ts"},"timelinehistory--no-history":{"id":"timelinehistory--no-history","title":"TimelineHistory","name":"No History","importPath":"./frontend/components/TimelineHistory.stories.ts"},"timelinehistory--horizontal":{"id":"timelinehistory--horizontal","title":"TimelineHistory","name":"Horizontal","importPath":"./frontend/components/TimelineHistory.stories.ts"},"timelinehistory--vertical":{"id":"timelinehistory--vertical","title":"TimelineHistory","name":"Vertical","importPath":"./frontend/components/TimelineHistory.stories.ts"},"timelinehistory--dynamic-vertical":{"id":"timelinehistory--dynamic-vertical","title":"TimelineHistory","name":"Dynamic Vertical","importPath":"./frontend/components/TimelineHistory.stories.ts"},"timelinehistory--dynamic-horizontal":{"id":"timelinehistory--dynamic-horizontal","title":"TimelineHistory","name":"Dynamic Horizontal","importPath":"./frontend/components/TimelineHistory.stories.ts"},"timelinehistory--dynamic-empty-horizontal":{"id":"timelinehistory--dynamic-empty-horizontal","title":"TimelineHistory","name":"Dynamic Empty Horizontal","importPath":"./frontend/components/TimelineHistory.stories.ts"}}}
